readPos/__init__.py
readPos/readPos.py
readPos-0.1.1.dist-info/LICENSE
readPos-0.1.1.dist-info/METADATA
readPos-0.1.1.dist-info/WHEEL
readPos-0.1.1.dist-info/top_level.txt
readPos-0.1.1.dist-info/RECORD
