Metadata-Version: 2.1
Name: readPos
Version: 0.1.1
Summary: Read plain text file data from csv map
Home-page: http://github.com/dmoralesl
Author: David Morales
Author-email: dmorales@odec.es
License: UNKNOWN
Platform: UNKNOWN
Classifier: Programming Language :: Python :: 3
Classifier: License :: OSI Approved :: MIT License
Classifier: Operating System :: OS Independent
Requires-Dist: pandas (>=0.25.3)
